zopf-0.0.1a1.dist-info/METADATA
zopf-0.0.1a1.dist-info/WHEEL
zopf-0.0.1a1.dist-info/entry_points.txt
zopf/__init__.py
zopf/__main__.py
zopf/_bindings.cpython-313t-x86_64-linux-gnu.so
zopf/_bindings.pyi
zopf/py.typed
zopf-0.0.1a1.dist-info/RECORD
