Metadata-Version: 2.4
Name: zopf
Version: 0.0.1a1
Classifier: Development Status :: 1 - Planning
Classifier: Programming Language :: Python
Summary: Python monorepo release management made easy
Home-Page: https://github.com/nougat-dev/zopf
Author-email: Eric Egli <43848365+eegli@users.noreply.github.com>
License: MIT OR Apache-2.0
Requires-Python: >=3.10
